{
  "categories" : [ {
    "category" : "POLITICS",
    "newsArticles" : [ {
      "id" : "tC2O3MyI",
      "imgUrl" : "https://image.kurier.at/images/original/4896988/46-173698828.jpg",
      "titleSource" : "Tiroler Politiker Hörl positiv: Vor Test mit Platter in Sitzung",
      "titleTarget" : "Tirolski političari i operater žičare Hörl testirali su pozitivno na Coronu",
      "url" : "https://kurier.at/politik/inland/tiroler-oevp-politiker-und-seilbahner-franz-hoerl-positiv-auf-corona-getestet/401168101"
    }, {
      "id" : "jWGCkIcS",
      "imgUrl" : "https://image.kurier.at/images/original/4897039/46-174237109.jpg",
      "titleSource" : "Anschober überarbeitet den Impfplan für Über-80-Jährige",
      "titleTarget" : "Anschober revidira plan cijepljenja",
      "url" : "https://kurier.at/politik/inland/anschober-ueberarbeitet-den-impfplan/401168158"
    }, {
      "id" : "59fKY9mu",
      "imgUrl" : "https://image.kurier.at/images/original/4896859/46-164600014.jpg",
      "titleSource" : "Lockdown-Entscheidung vertagt, \"Schulschließungen leider effektiv\"",
      "titleTarget" : "Odgođena odluka o zaključavanju, \"zatvaranje škola nažalost na snazi\"",
      "url" : "https://kurier.at/politik/inland/lockdown-entscheidung-vertagt-virologin-schulschliessungen-leider-effektiv/401168005"
    }, {
      "id" : "gTtfvKYH",
      "imgUrl" : "https://image.kurier.at/images/original/4897372/46-174137422.jpg",
      "titleSource" : "Rendi-Wagner für Krisenproduktion von Covid-Impfstoffen in Europa",
      "titleTarget" : "Rendi-Wagner za kriznu proizvodnju Covid cjepiva u Europi",
      "url" : "https://kurier.at/politik/inland/rendi-wagner-fuer-krisenproduktion-von-covid-impfstoffen-in-europa/401168362"
    }, {
      "id" : "mTv7HucS",
      "imgUrl" : "https://image.kurier.at/images/original/4842618/46-173750498.jpg",
      "titleSource" : "Anschober über Lieferprobleme bei Astra Zeneca: \"Wollen konkrete Liefertermine\"",
      "titleTarget" : "Anschober o problemima s isporukom u Astra Zeneci: \"Želite određene datume isporuke\"",
      "url" : "https://kurier.at/politik/inland/anschober-ueber-lieferprobleme-bei-astrazeneca-wollen-konkrete-liefertermine/401168029"
    }, {
      "id" : "WTxdmPP5",
      "imgUrl" : "https://image.kurier.at/images/original/4898758/46-173484944.jpg",
      "titleSource" : "Kaiser über Astra Zeneca: \"Ist hier jemand betrogen worden?'\"",
      "titleTarget" : "Kaiser o Astra Zeneci: \"Je li ovdje netko izdan?\"",
      "url" : "https://kurier.at/politik/inland/kaiser-ueber-astra-zeneca-ist-hier-jemand-betrogen-worden/401169088"
    }, {
      "id" : "mrvMs14L",
      "imgUrl" : "https://image.kurier.at/images/original/4898758/46-173484944.jpg",
      "titleSource" : "Kaiser über AstraZeneca: \"Ist hier jemand betrogen worden?'\"",
      "titleTarget" : "Kaiser na AstraZeneci: \"Je li ovdje netko izdan?\"",
      "url" : "https://kurier.at/politik/inland/kaiser-ueber-astrazeneca-ist-hier-jemand-betrogen-worden/401169088"
    } ]
  }, {
    "category" : "ECONOMICS",
    "newsArticles" : [ {
      "id" : "79Co2r5H",
      "imgUrl" : "https://image.kurier.at/images/original/321975/flugzeug-000_Reinhard%252BVogel.jpg",
      "titleSource" : "Nur noch mit Test oder Impfung ins Flugzeug",
      "titleTarget" : " Samo testom ili cijepljenjem u avionu",
      "url" : "https://kurier.at/wirtschaft/fliegen-ab-sommer-nur-noch-mit-negativem-test/401168512"
    }, {
      "id" : "qFMOxPVp",
      "imgUrl" : "https://image.kurier.at/images/original/4898125/46-174874317.jpg",
      "titleSource" : "„Wiederaufbau-Trio“ feilt an Vision 2040",
      "titleTarget" : "\"Rekonstrukcijski trio\" radi na Visionu 2040",
      "url" : "https://kurier.at/wirtschaft/wiederaufbau-trio-feilt-an-vision-2040/401168851"
    }, {
      "id" : "yY4ayWE0",
      "imgUrl" : "https://image.kurier.at/images/original/3435895/46-129540686.jpg",
      "titleSource" : "Bad, Sofa oder neue Küche? Leiner versteigert 40.000 Artikel",
      "titleTarget" : "Kupaonica, kauč ili nova kuhinja? Leiner daje na aukciju 40.000 predmeta",
      "url" : "https://kurier.at/wirtschaft/bad-sofa-oder-neue-kueche-leiner-versteigert-40000-artikel/401168218"
    }, {
      "id" : "gvTw5LIv",
      "imgUrl" : "https://image.kurier.at/images/original/4896892/46-90377577.jpg",
      "titleSource" : "Lehrgang für Aufsichtsräte: Junger Schwung in die alte Welt",
      "titleTarget" : "Tečaj za nadzorne odbore: mladi zamah u starom svijetu",
      "url" : "https://kurier.at/wirtschaft/karriere/lehrgang-fuer-aufsichtsraete-junger-schwung-in-die-alte-welt/401168023"
    }, {
      "id" : "DTrpuaxc",
      "imgUrl" : "https://image.kurier.at/images/original/4867158/20210112-ABD0058-1-1.jpg",
      "titleSource" : "Nochmals zwei Milliarden mehr für Kurzarbeit",
      "titleTarget" : "Još dvije milijarde više za kratkotrajni rad",
      "url" : "https://kurier.at/wirtschaft/nochmals-zwei-milliarden-mehr-fuer-kurzarbeit/401168350"
    }, {
      "id" : "Ze0CupO1",
      "imgUrl" : "https://image.kurier.at/images/original/4629332/20200911-ABD0001-1-1.jpg",
      "titleSource" : "MAN droht mit Verkauf oder Schließung des Werks in Steyr",
      "titleTarget" : "MAN prijeti prodajom ili zatvaranjem tvornice u Steyru",
      "url" : "https://kurier.at/wirtschaft/man-droht-mit-verkauf-oder-schliessung-des-werks-in-steyr/401168659"
    }, {
      "id" : "kNETDG9x",
      "imgUrl" : "https://image.kurier.at/images/original/3263399/46-143749962.jpg",
      "titleSource" : "Bestellplattform Mjam eröffnet Online-Supermarkt",
      "titleTarget" : "Platforma za naručivanje Mjam otvara internetski supermarket",
      "url" : "https://kurier.at/wirtschaft/bestellplattform-mjam-eroeffnet-online-supermarkt/401168467"
    } ]
  }, {
    "category" : "CHRONICLE",
    "newsArticles" : [ {
      "id" : "JRAUnm5K",
      "imgUrl" : "https://oekastatic.orf.at/mims/2021/04/40/crops/w=1280/821408_opener_286440_image_4.jpg?s=4c568d850321478f49360c8bff2b2abbc4e1e8e1",
      "titleSource" : "Frischer Wind beim Haldenlift in Schwarzenberg",
      "titleTarget" : "Dašak svježeg zraka u Haldenliftu u Schwarzenbergu",
      "url" : "https://vorarlberg.orf.at/stories/3086377/"
    }, {
      "id" : "EouaEvVS",
      "imgUrl" : "https://image.kurier.at/images/original/4896642/46-174321841.jpg",
      "titleSource" : "Burger-Boom in Wien: Zwei Typen gegen \"Five Guys\"",
      "titleTarget" : "Burger-procvat u Beču: dvojica protiv \"Five Guys\"",
      "url" : "https://kurier.at/chronik/oesterreich/burger-boom-in-wien-zwei-typen-gegen-five-guys/401167827"
    }, {
      "id" : "2m5sCUSt",
      "imgUrl" : "https://image.kurier.at/images/original/4243085/46-106892127.jpg",
      "titleSource" : "Fast die Hälfte der Todesfälle in Alters- und Pflegeheimen",
      "titleTarget" : "Gotovo polovica smrtnih slučajeva u domovima umirovljenika i njega",
      "url" : "https://kurier.at/chronik/oesterreich/fast-die-haelfte-der-todesfaelle-in-alters-und-pflegeheimen/401167999"
    }, {
      "id" : "8P0tdH9m",
      "imgUrl" : "https://image.kurier.at/images/original/4897630/46-77781501.jpg",
      "titleSource" : "80 belgische Soldaten bereits in Tirol: Abgeschottet auf 2.000 Meter",
      "titleTarget" : "80 belgijskih vojnika već u Tirolu: zapečaćeno na 2000 metara",
      "url" : "https://kurier.at/chronik/oesterreich/80-belgische-soldaten-sollen-fuer-ausbildung-nach-tirol-kommen/401168128"
    }, {
      "id" : "ORD5jsyG",
      "imgUrl" : "https://media.diepresse.com/images/uploads_500/3/e/a/5927914/Themenbild-Corona-Eine-junge-Frau-mit-Schutzmaske-MundschutzFFP2-KN95-medizinische-Maske-Community-Maske-blickt-sorg_161165909838635_v0_h.jpg",
      "titleSource" : "Was es mit den KN95-Masken auf sich hat",
      "titleTarget" : "O čemu se radi u maskama KN95",
      "url" : "https://www.diepresse.com/5927914/Masken_Was-es-mit-den-KN95Masken-auf-sich-hat?from=rss"
    }, {
      "id" : "XHmWvGgb",
      "titleSource" : "Neue Chancen für junge Barkeeper",
      "titleTarget" : "Nove mogućnosti za mlade barmene",
      "url" : "https://salzburg.orf.at/stories/3086982/"
    }, {
      "id" : "zIolOVIl",
      "imgUrl" : "https://image.kurier.at/images/original/4764708/illu_corona_statistik%20%283%29_0.png",
      "titleSource" : "1.417 neue Corona-Infektionen in Österreich",
      "titleTarget" : "1.417 novih infekcija koronom u Austriji",
      "url" : "https://kurier.at/chronik/oesterreich/1417-neue-corona-infektionen-in-oesterreich/401168155"
    } ]
  }, {
    "category" : "CULTURE",
    "newsArticles" : [ {
      "id" : "TkWX9NK4",
      "imgUrl" : "https://image.kurier.at/images/original/4898173/46-174910604.jpg",
      "titleSource" : "Autor Lars Norén starb 76-jährig an den Folgen von Covid-19",
      "titleTarget" : "Autor Lars Norén umro je u 76. godini od Covid-19",
      "url" : "https://kurier.at/kultur/autor-lars-noren-starb-76-jaehrig-an-den-folgen-von-covid-19/401168890"
    }, {
      "id" : "v2dQ3bre",
      "imgUrl" : "https://image.kurier.at/images/original/4897354/46-164529600.jpg",
      "titleSource" : "Auktionsrekord: 408.000 US-Dollar für ein Set von Pokémon-Karten",
      "titleTarget" : "Zapis na aukciji: 408 000 USD za set Pokémon karata",
      "url" : "https://kurier.at/kultur/auktionsrekord-408000-us-dollar-fuer-ein-set-von-pokemon-karten/401168422"
    }, {
      "id" : "J5XsxOnP",
      "imgUrl" : "https://image.kurier.at/images/original/4896964/46-147684116.jpg",
      "titleSource" : "Minus 199 Milliarden Euro: Coronakrise beutelt europäische Kulturwirtschaft",
      "titleTarget" : "Minus 199 milijardi eura: Koronska kriza šokira europsku kulturnu industriju",
      "url" : "https://kurier.at/kultur/minus-199-mrd-euro-coronakrise-beutelt-europaeische-kulturwirtschaft/401168089"
    }, {
      "id" : "H8cNQPub",
      "imgUrl" : "https://image.kurier.at/images/original/4897951/46-174908252.jpg",
      "titleSource" : "Schalkos \"Ich und die Anderen\" feiert in Berlin Premiere",
      "titleTarget" : "Schalkova premijera \"Ja i ostali\" u Berlinu",
      "url" : "https://kurier.at/kultur/schalkos-ich-und-die-anderen-feiert-in-berlin-premiere/401168785"
    }, {
      "id" : "ZSarr0c7",
      "imgUrl" : "https://image.kurier.at/images/original/3075861/46-130156133.jpg",
      "titleSource" : "Kochen mit Spotify: Barillas Playlists verraten, wann die Spaghetti al dente sind",
      "titleTarget" : "Kuhanje sa Spotifyjem: Barillini popisi pjesama otkrivaju kada su špageti al dente",
      "url" : "https://kurier.at/kultur/medien/kochen-mit-spotify-barillas-playlists-verraten-wann-die-spaghetti-al-dente-sind/401168614"
    }, {
      "id" : "DMBPeY5L",
      "imgUrl" : "https://media.diepresse.com/images/uploads_500/3/4/d/5927757/FE0732A6-1C81-44D6-A0A1-8E15D43FD5F6_v0_l.jpg",
      "titleSource" : "\"Die Ausgrabung\": So spannend kann Buddeln sein",
      "titleTarget" : "\"Iskop\": kopanje može biti tako uzbudljivo",
      "url" : "https://www.diepresse.com/5927757/Film_Die-Ausgrabung_So-spannend-kann-Buddeln-sein?from=rss"
    }, {
      "id" : "ArCoevyL",
      "imgUrl" : "https://media.diepresse.com/images/uploads_500/4/0/e/5927950/blouds_1611657479993459.jpg",
      "titleSource" : "Die zehn besten Filme 2020 - für das American Film Institute",
      "titleTarget" : "Deset najboljih filmova 2020. - za Američki filmski institut",
      "url" : "https://www.diepresse.com/5927950/Ausgezeichnet_Die-zehn-besten-Filme-2020-fuer-das-American-Film?from=rss"
    } ]
  }, {
    "category" : "HEALTH",
    "newsArticles" : [ ]
  }, {
    "category" : "SPORT",
    "newsArticles" : [ {
      "id" : "SDnAI7lP",
      "titleSource" : "Furioser Schwarz krallt sich Schladming-Sieg",
      "titleTarget" : "Bijesne crne kandže pobjeda Schladminga",
      "url" : "https://sport.orf.at/stories/3072360/"
    }, {
      "id" : "O66m6VJ8",
      "titleSource" : "Baumgartlingers EM-Chance lebt",
      "titleTarget" : "Baumgartlingerova EM šansa je živa",
      "url" : "https://sport.orf.at/stories/3072345/"
    }, {
      "id" : "Hc21N1Lp",
      "imgUrl" : "https://image.kurier.at/images/original/4898533/46-174973854.jpg",
      "titleSource" : "Schneetreiben: Rapid - St. Pölten auf Mittwochabend verschoben",
      "titleTarget" : "Nanosi snijega: Brz - St. Pölten odgođen za srijedu navečer",
      "url" : "https://kurier.at/sport/fussball/reges-schneetreiben-bundesliga-spiel-rapid-st-poelten-abgesagt/401169049"
    }, {
      "id" : "0STfRunn",
      "titleSource" : "ÖSV-Techniker für Schladming bereit",
      "titleTarget" : "ÖSV tehničari spremni za Schladming",
      "url" : "https://sport.orf.at/stories/3072297/"
    }, {
      "id" : "4fo9k9oR",
      "imgUrl" : "https://image.kurier.at/images/original/4897624/46-174137316.jpg",
      "titleSource" : "Schulden im Milliardenbereich: So schlecht steht Barca wirklich da",
      "titleTarget" : "Milijarde dugova: toliko je Barca zaista teška",
      "url" : "https://kurier.at/sport/fussball/ueber-1-milliarde-euro-schulden-so-schlecht-steht-der-fc-barcelona-wirklich-da/401168449"
    }, {
      "id" : "wFJBVVXB",
      "imgUrl" : "https://image.kurier.at/images/original/4898317/46-174941949.jpg",
      "titleSource" : "Halbzeitführung für Feller beim Night Race in Schladming",
      "titleTarget" : "Turneja na poluvremenu za Fellera na Noćnoj utrci u Schladmingu",
      "url" : "https://kurier.at/sport/wintersport/ski-alpin-halbzeitfuehrung-fuer-manuel-feller-beim-night-race-in-schladming/401168968"
    }, {
      "id" : "RaODMRBT",
      "titleSource" : "Barca-Schulden klettern in enorme Höhen",
      "titleTarget" : "Barcin dug vrtoglavo raste",
      "url" : "https://sport.orf.at/stories/3072340/"
    } ]
  } ],
  "country" : "austria",
  "language" : "serbocroatian"
}