{
  "categories" : [ {
    "category" : "POLITICS",
    "newsArticles" : [ {
      "id" : "zIMYwTVl",
      "imgUrl" : "https://image.kurier.at/images/original/4863828/20210110-ABD0066-1-1.jpg",
      "titleSource" : "Kurz machen geimpfte Bürgermeister \"zornig\"",
      "titleTarget" : "Ukratko, cijepljeni gradonačelnici vas čine \"bijesnima\"",
      "url" : "https://kurier.at/politik/inland/kurz-machen-geimpfte-buergermeister-zornig/401161806"
    }, {
      "id" : "rSsgXaA2",
      "imgUrl" : "https://image.kurier.at/images/original/4883181/20210120-ABD0033-1-1.jpg",
      "titleSource" : "Kogler zu Wirtschaftshilfen: \"'Alles, was es braucht' gilt immer noch\"",
      "titleTarget" : "Kogler o ekonomskoj pomoći: \"\" Sve što je potrebno \"i dalje vrijedi\"",
      "url" : "https://kurier.at/politik/inland/alles-was-es-braucht-gilt-immer-noch/401161629"
    }, {
      "id" : "y5j5lLdM",
      "imgUrl" : "https://image.kurier.at/images/original/3681923/20190805-ABD0005-1-1.jpg",
      "titleSource" : "Parteienförderung: ÖVP für Einfrieren, Grüne fordern mehr Transparenz",
      "titleTarget" : "Promocija političkih stranaka: ÖVP za zamrzavanje, Zeleni traže veću transparentnost",
      "url" : "https://kurier.at/politik/inland/parteienfoerderung-oevp-fuer-einfrieren-gruene-fordern-mehr-transparenz/401162145"
    }, {
      "id" : "BT5YPC4z",
      "imgUrl" : "https://image.kurier.at/images/original/4883547/20210120-ABD0065-1-1.jpg",
      "titleSource" : "Nationalrat: Raab nun auch Familienministerin",
      "titleTarget" : "Nacionalno vijeće: Raab je sada i ministar obitelji",
      "url" : "https://kurier.at/politik/inland/nationalrat-raab-nun-auch-familienministerin/401162283"
    }, {
      "id" : "uogSm2bF",
      "imgUrl" : "https://image.kurier.at/images/original/4869561/20210113-ABD0013-1-1.jpg",
      "titleSource" : "Blümel hat Budget- und Präsidialsektion neu besetzt",
      "titleTarget" : "Blümel je regrutirao proračunske i predsjedničke odsjeke",
      "url" : "https://kurier.at/politik/inland/bluemel-hat-budget-und-praesidialsektion-neu-besetzt/401162040"
    }, {
      "id" : "VMkGqQGW",
      "imgUrl" : "https://image.kurier.at/images/original/4882557/46-174160390.jpg",
      "titleSource" : "Rektoren-Chefin Seidler fürchtet mehr Studienabbrüche",
      "titleTarget" : "Rektorski šef Seidler boji se još odustajanja",
      "url" : "https://kurier.at/politik/inland/rektoren-chefin-seidler-fuerchtet-mehr-studienabbrueche/401161392"
    }, {
      "id" : "Fw4M0Ry1",
      "imgUrl" : "https://media.diepresse.com/images/uploads_500/a/0/c/5925388/Biden_h.jpg",
      "titleSource" : "Joe Biden ist neuer US-Präsident",
      "titleTarget" : "Joe Biden novi je američki predsjednik",
      "url" : "https://www.diepresse.com/5925388/TickerNachlese_Joe-Biden-ist-neuer-USPraesident?from=rss"
    } ]
  }, {
    "category" : "ECONOMICS",
    "newsArticles" : [ {
      "id" : "tRxJPfVe",
      "imgUrl" : "https://image.kurier.at/images/original/3779786/78370011350597492_BLD_Online.jpg",
      "titleSource" : "Nachzahlung für Arbeitslose in Schulungen und Reha",
      "titleTarget" : "Doplata za nezaposlene na osposobljavanju i rehabilitaciji",
      "url" : "https://kurier.at/wirtschaft/nachzahlung-fuer-arbeitslose-in-schulungen-und-reha/401162178"
    }, {
      "id" : "MR8r7LEN",
      "imgUrl" : "https://image.kurier.at/images/original/3785816/78370011350638546_BLD_Online.jpg",
      "titleSource" : "Douglas soll europaweit 500 Filialen schließen",
      "titleTarget" : "Douglas će zatvoriti 500 podružnica diljem Europe",
      "url" : "https://kurier.at/wirtschaft/douglas-soll-europaweit-500-filialen-zu-schliessen/401162361"
    }, {
      "id" : "ZvxP8r96",
      "imgUrl" : "https://image.kurier.at/images/original/4884375/46-143501589.jpg",
      "titleSource" : "Aus nach 400 Jahren für Salzburger Bäckerei",
      "titleTarget" : "Nakon 400 godina za salzburšku pekaru",
      "url" : "https://kurier.at/wirtschaft/aus-nach-400-jahren-fuer-salzburger-baeckerei/401162385"
    }, {
      "id" : "3yzpGFmK",
      "imgUrl" : "https://image.kurier.at/images/original/3760907/81771351250459672_BLD_Online.jpg",
      "titleSource" : "Top-Manager starten Initiative gegen Klimawandel",
      "titleTarget" : "Top menadžeri pokreću inicijativu protiv klimatskih promjena",
      "url" : "https://kurier.at/wirtschaft/top-manager-starten-initiative-gegen-klimawandel/401162115"
    }, {
      "id" : "RrUACnun",
      "imgUrl" : "https://image.kurier.at/images/original/4882854/46-174095220.jpg",
      "titleSource" : "Neue Datenschutzregeln bei WhatsApp: Änderungen \"kosmetischer Natur\"",
      "titleTarget" : "Nova pravila o zaštiti podataka za WhatsApp: promjene \"kozmetičke prirode\"",
      "url" : "https://kurier.at/wirtschaft/neue-datenschutzregeln-bei-whatsapp-aenderungen-kosmetischer-natur/401161578"
    }, {
      "id" : "BYoCmL7L",
      "imgUrl" : "https://media.diepresse.com/images/uploads/a/8/7/5925511/-THEMENBILD--CORONA-DRITTER-LOCKDOWN--HANDEL_1611157949678471_v0_l.jpg",
      "titleSource" : "Sonderregeln im Insolvenzrecht: Nicht alle Gläubiger sind gleich",
      "titleTarget" : "Posebna pravila u stečajnom zakonu: nisu svi vjerovnici jednaki",
      "url" : "https://www.diepresse.com/5925511/CovidSondergesetze_Sonderregeln-im-Insolvenzrecht_Nicht-alle?from=rss"
    }, {
      "id" : "UW0N2d5L",
      "imgUrl" : "https://image.kurier.at/images/original/1009305/supermarkt.jpg",
      "titleSource" : "Mieten, Strom und Lebensmittel treiben Inflation",
      "titleTarget" : "Najam, struja i hrana pokretači su inflacije",
      "url" : "https://kurier.at/wirtschaft/inflation-sank-2020-auf-14-prozent/401161668"
    } ]
  }, {
    "category" : "CHRONICLE",
    "newsArticles" : [ {
      "id" : "2AJsH2fN",
      "imgUrl" : "https://image.kurier.at/images/original/4883391/46-173551542.jpg",
      "titleSource" : "Tiroler Corona-Vollquarantäne war rechtswidrig",
      "titleTarget" : "Karantena pune korone u Tirolu bila je ilegalna",
      "url" : "https://kurier.at/chronik/oesterreich/tiroler-corona-vollquarantaene-war-rechtswidrig/401161998"
    }, {
      "id" : "L9yJPB4w",
      "imgUrl" : "https://image.kurier.at/images/original/4879722/ffp2-mask-5590112_1920.jpg",
      "titleSource" : "FFP2-Masken ab 59 Cent erhältlich",
      "titleTarget" : "FFP2 maske dostupne su od 59 centi",
      "url" : "https://kurier.at/chronik/oesterreich/ffp2-masken-bei-diskonter-um-59-cent/401162331"
    }, {
      "id" : "3pv1OPfE",
      "imgUrl" : "https://image.kurier.at/images/original/4797984/20201203-ABD0092-1-1.jpg",
      "titleSource" : "3,8 Millionen Biontech-Impfdosen zusätzlich für Österreich",
      "titleTarget" : "3,8 milijuna dodatnih doza cjepiva Biontech za Austriju",
      "url" : "https://kurier.at/chronik/oesterreich/38-millionen-biontech-impfdosen-zusaetzlich-fuer-oesterreich/401162112"
    }, {
      "id" : "5lUViHh1",
      "imgUrl" : "https://oekastatic.orf.at/mims/2021/04/58/crops/w=1280/819676_opener_285858_20210120_situation_kindergaerten_00_02_15_14.jpg?s=5485acce8c76a520bdce5e57645335a65c7475b8",
      "titleSource" : "Kindergärtnerinnen fordern besseren Schutz",
      "titleTarget" : "Odgajatelji u vrtićima zahtijevaju bolju zaštitu",
      "url" : "https://kaernten.orf.at/stories/3085976/"
    }, {
      "id" : "knSkjbzh",
      "imgUrl" : "https://image.kurier.at/images/original/4883757/46-174181557.jpg",
      "titleSource" : "Ärztin wetterte bei Corona-Demo gegen \"Gesundheitsdiktatur\"",
      "titleTarget" : "Doktor je na demonstracijama Corone ometao \"zdravstvenu diktaturu\"",
      "url" : "https://kurier.at/chronik/oesterreich/aerztin-bei-corona-demo-alte-werden-mit-impfstoffen-erledigt/401161977"
    }, {
      "id" : "xmf3gD4N",
      "imgUrl" : "https://image.kurier.at/images/original/4764708/illu_corona_statistik%20%283%29_0.png",
      "titleSource" : "1.671 neue Corona-Infektionen in Österreich",
      "titleTarget" : "1.671 nova infekcija koronom u Austriji",
      "url" : "https://kurier.at/chronik/oesterreich/1671-neue-corona-infektionen-in-oesterreich/401161611"
    }, {
      "id" : "3YnPquqJ",
      "imgUrl" : "https://image.kurier.at/images/original/3868184/78350011451286856_BLD_Online.jpg",
      "titleSource" : "Erneutes Erdbeben in der Obersteiermark",
      "titleTarget" : "Još jedan potres u Gornjoj Štajerskoj",
      "url" : "https://kurier.at/chronik/oesterreich/erneutes-erdbeben-im-sueden-oesterreich/401161647"
    } ]
  }, {
    "category" : "CULTURE",
    "newsArticles" : [ {
      "id" : "0IN9IEZz",
      "imgUrl" : "https://image.kurier.at/images/original/4884642/46-174178680.jpg",
      "titleSource" : "Verfilmung von Franz Klammers Olympiasieg: Österreichs Mondlandung",
      "titleTarget" : "Filmska adaptacija olimpijske pobjede Franza Klammera: Austrijsko slijetanje na mjesec",
      "url" : "https://kurier.at/kultur/verfilmung-von-franz-klammers-olympiasieg-oesterreichs-mondlandung/401162526"
    }, {
      "id" : "ABHGBol2",
      "imgUrl" : "https://image.kurier.at/images/original/4882464/46-61099034.jpg",
      "titleSource" : "... und wieder 18 Bücher, ganz kurz",
      "titleTarget" : "... i opet 18 knjiga, vrlo kratko",
      "url" : "https://kurier.at/kultur/buch/und-wieder-18-buecher-ganz-kurz/401161356"
    }, {
      "id" : "OYcB7XAM",
      "imgUrl" : "https://image.kurier.at/images/original/4882617/46-174156871.jpg",
      "titleSource" : "\"Sörensen hat Angst\": Bjarne Mädel als kauziger Ermittler",
      "titleTarget" : "\"Sörensen se boji\": Bjarne Mädel kao znatiželjni istražitelj",
      "url" : "https://kurier.at/kultur/medien/soerensen-hat-angst-bjarne-maedel-als-kauziger-ermittler/401161425"
    }, {
      "id" : "cwumNT7A",
      "imgUrl" : "https://image.kurier.at/images/original/4878303/46-174056196.jpg",
      "titleSource" : "Henk Schiffmachers \"Tattoo\": Der Körper als Tagebuch",
      "titleTarget" : "\"Tetovaža\" Henka Schiffmachera: Tijelo kao dnevnik",
      "url" : "https://kurier.at/kultur/henk-schiffmachers-tattoo-der-koerper-als-tagebuch/401158902"
    }, {
      "id" : "qMDXJU4e",
      "imgUrl" : "https://image.kurier.at/images/original/4884921/46-174190227.jpg",
      "titleSource" : "Das A-dieu-Team: ORF1 setzt Marolt-Sendung vorzeitig ab",
      "titleTarget" : "A-dieu tim: ORF1 otkazuje emitiranje Marolta rano",
      "url" : "https://kurier.at/kultur/medien/das-a-dieu-team-orf1-setzt-marolt-sendung-vorzeitig-ab/401162583"
    }, {
      "id" : "LCVzxd53",
      "imgUrl" : "https://image.kurier.at/images/original/4884765/46-107207284.jpg",
      "titleSource" : "Skifilme: Zwei Brettl’, a g’führiger Schnee – aber nicht immer Juchhe",
      "titleTarget" : "Skijaški filmovi: Dvije ploče, puno snijega - ali ne uvijek sjajno",
      "url" : "https://kurier.at/kultur/skifilme-zwei-brettl-a-gfuehriger-schnee-aber-nicht-immer-juchhe/401162523"
    }, {
      "id" : "giCXYABk",
      "imgUrl" : "https://image.kurier.at/images/original/4882887/46-101811715.jpg",
      "titleSource" : "Musiker Van Morrison will gegen Kulturlockdown klagen",
      "titleTarget" : "Glazbenik Van Morrison želi tužiti protiv zatvaranja kulture",
      "url" : "https://kurier.at/kultur/musiker-van-morrison-will-gegen-kulturlockdown-klagen/401161620"
    } ]
  }, {
    "category" : "HEALTH",
    "newsArticles" : [ ]
  }, {
    "category" : "SPORT",
    "newsArticles" : [ {
      "id" : "PTRviDb2",
      "imgUrl" : "https://image.kurier.at/images/original/4883235/46-173934891.jpg",
      "titleSource" : "Gregor Schlierenzauer fliegt aus dem Weltcup-Team",
      "titleTarget" : "Gregor Schlierenzauer izbačen je iz momčadi Svjetskog kupa",
      "url" : "https://kurier.at/sport/wintersport/gregor-schlierenzauer-fliegt-aus-dem-weltcup-team/401161917"
    }, {
      "id" : "FJAW8a3U",
      "titleSource" : "Quarterback-Star Rivers beendet NFL-Karriere",
      "titleTarget" : "Quarterback zvijezda Rivers završava NFL karijeru",
      "url" : "https://sport.orf.at/stories/3072065/"
    }, {
      "id" : "1EMaY5yK",
      "imgUrl" : "https://image.kurier.at/images/original/4884069/46-169053739.jpg",
      "titleSource" : "Sturm-Trainer Ilzer will die Fountas-Sperre nicht überbewerten",
      "titleTarget" : "Trener Sturma Ilzer ne želi precijeniti zabranu Fountasa",
      "url" : "https://kurier.at/sport/fussball/sturm-trainer-ilzer-will-vor-dem-duell-mit-rapid-die-fountas-sperre-nicht-ueberbewerten/401162265"
    }, {
      "id" : "Rjdpnk5U",
      "imgUrl" : "https://image.kurier.at/images/original/4885083/46-174185085.jpg",
      "titleSource" : "Der nächste Sturz: Saisonende für Pechvogel Nina Ortlieb",
      "titleTarget" : "Sljedeća jesen: kraj sezone za nesretnu Ninu Ortlieb",
      "url" : "https://kurier.at/sport/wintersport/der-naechste-sturz-pechvogel-nina-ortlieb-landet-im-spital/401162214"
    }, {
      "id" : "qAKNRfSb",
      "titleSource" : "WM nimmt in Monte Carlo Fahrt auf",
      "titleTarget" : "WM ubrzava u Monte Carlu",
      "url" : "https://sport.orf.at/stories/3072016/"
    }, {
      "id" : "QhEGBwQc",
      "titleSource" : "Ortlieb droht nach Sturz Saisonende",
      "titleTarget" : "Ortlieb prijeti završnicom sezone nakon svog pada",
      "url" : "https://sport.orf.at/stories/3072059/"
    }, {
      "id" : "gHPlnQTP",
      "titleSource" : "Offensivspieler Möschl zurück bei Ried",
      "titleTarget" : "Ofanzivni igrač Möschl vratio se u Ried",
      "url" : "https://sport.orf.at/stories/3072072/"
    } ]
  } ],
  "country" : "austria",
  "language" : "serbocroatian"
}