{
  "id" : "h9T6eVOA",
  "url" : "https://kurier.at/sport/fussball/nach-zinedine-zidanes-wutrede-real-madrid-gewann-bei-huesca-21/401180668",
  "category" : "SPORT",
  "publisher" : "kurier.at",
  "publishedOn" : "2021-02-06T18:09:36Z[UTC]",
  "imageUrl" : "https://image.kurier.at/images/original/4922458/46-175500874.jpg",
  "imageCopyright" : "EPA / JAVIER CEBOLLADA",
  "sourceCountry" : "austria",
  "sourceLanguage" : "german",
  "targetLanguage" : "serbocroatian",
  "articleTitle" : "Nach Zidanes Wutrede: Real Madrid gewann bei Huesca 2:1",
  "articleTitleTranslated" : "Nakon Zidaneova ljutitog govora: Real Madrid je pobijedio 2-1 na Huesci",
  "articleContent" : [ "Der Real-Coach hatte sich zuletzt lautstark über die Berichterstattung beklagt. Sein Team reagierte." ],
  "articleContentTranslated" : [ "Pravi trener nedavno se glasno žalio na izvještavanje. Njegov je tim reagirao." ]
}