{
  "id" : "shxBn7wl",
  "url" : "https://kurier.at/wirtschaft/dr-martens-zum-boersendebuet-mit-37-mrd-pfund-bewertet/401172034",
  "category" : "ECONOMICS",
  "publisher" : "kurier.at",
  "publishedOn" : "2021-01-29T08:58:29Z[UTC]",
  "imageUrl" : "https://image.kurier.at/images/original/4903786/46-175197024.jpg",
  "sourceCountry" : "austria",
  "sourceLanguage" : "german",
  "targetLanguage" : "serbocroatian",
  "articleTitle" : "Dr. Martens zum Börsendebüt mit 3,7 Mrd. Pfund bewertet",
  "articleTitleTranslated" : "Dr. Martens je na svom debiju na berzi procijenio 3,7 milijardi funti",
  "articleContent" : [ "Vor sieben Jahren zahlte Finanzinvestor Permira gerade einmal 380 Mio. Euro für den Kult-Schuhhersteller." ],
  "articleContentTranslated" : [ "Prije sedam godina, financijski investitor Permira platio je samo 380 milijuna eura za kultnog proizvođača cipela." ]
}